{
  "openapi": "3.0.0",
  "info": {
    "title": "Bicep Extensibility Provider API",
    "version": "2.0.0"
  },
  "tags": [],
  "paths": {
    "/{extensionVersion}/longRunningOperation/get": {
      "post": {
        "operationId": "getLongRunningOperation",
        "description": "Retrieve the status of a long-running operation.\n\nA Failure response indicates an issue retrieving the operation status\n(e.g., network errors), NOT a failure of the operation itself.\nOperation failures are reported via the operation's status field.\n\nSee the [contract documentation](https://github.com/Azure/bicep-extensibility/blob/main/docs/v2/contract.md#get-long-running-operation)\nfor detailed requirements.",
        "parameters": [
          {
            "$ref": "#/components/parameters/RequestParams.extensionVersion"
          },
          {
            "$ref": "#/components/parameters/RequestHeaders.clientRequestId"
          },
          {
            "$ref": "#/components/parameters/RequestHeaders.correlationRequestId"
          },
          {
            "$ref": "#/components/parameters/RequestHeaders.clientTenantId"
          },
          {
            "$ref": "#/components/parameters/RequestHeaders.homeTenantId"
          },
          {
            "$ref": "#/components/parameters/RequestHeaders.acceptLanguage"
          },
          {
            "$ref": "#/components/parameters/RequestHeaders.referer"
          },
          {
            "$ref": "#/components/parameters/RequestHeaders.traceparent"
          },
          {
            "$ref": "#/components/parameters/RequestHeaders.tracestate"
          }
        ],
        "responses": {
          "200": {
            "description": "Standard 200 OK response.",
            "headers": {
              "x-ms-request-id": {
                "required": true,
                "description": "Server-generated request ID.",
                "schema": {
                  "type": "string"
                }
              },
              "Date": {
                "required": true,
                "description": "The date the request was processed, in RFC 7231 format.",
                "schema": {
                  "type": "string"
                }
              }
            },
            "content": {
              "application/json": {
                "schema": {
                  "$ref": "#/components/schemas/LongRunningOperation"
                }
              }
            }
          },
          "4XX": {
            "description": "Generic error response for 4xx and 5xx status codes.",
            "headers": {
              "x-ms-request-id": {
                "required": true,
                "description": "Server-generated request ID.",
                "schema": {
                  "type": "string"
                }
              },
              "Date": {
                "required": true,
                "description": "The date the request was processed, in RFC 7231 format.",
                "schema": {
                  "type": "string"
                }
              }
            },
            "content": {
              "application/json": {
                "schema": {
                  "$ref": "#/components/schemas/ErrorResponse"
                }
              }
            }
          },
          "5XX": {
            "description": "Generic error response for 4xx and 5xx status codes.",
            "headers": {
              "x-ms-request-id": {
                "required": true,
                "description": "Server-generated request ID.",
                "schema": {
                  "type": "string"
                }
              },
              "Date": {
                "required": true,
                "description": "The date the request was processed, in RFC 7231 format.",
                "schema": {
                  "type": "string"
                }
              }
            },
            "content": {
              "application/json": {
                "schema": {
                  "$ref": "#/components/schemas/ErrorResponse"
                }
              }
            }
          }
        },
        "externalDocs": {
          "url": "https://github.com/Azure/bicep-extensibility/blob/main/docs/v2/contract.md#get-long-running-operation",
          "description": "Get Long-Running Operation Contract"
        },
        "requestBody": {
          "required": true,
          "content": {
            "application/json": {
              "schema": {
                "type": "object",
                "additionalProperties": {}
              }
            }
          }
        }
      }
    },
    "/{extensionVersion}/resource/createOrUpdate": {
      "post": {
        "operationId": "createOrUpdateResource",
        "description": "Create or update a resource.\n\nReturns 200 OK with the resource if the operation completes synchronously,\nor 202 Accepted with a LongRunningOperation if it is long-running.\n\nSee the [contract documentation](https://github.com/Azure/bicep-extensibility/blob/main/docs/v2/contract.md#create-or-update-resource)\nfor detailed requirements including identifiers, configuration echoing, and configuration ID.",
        "parameters": [
          {
            "$ref": "#/components/parameters/RequestParams.extensionVersion"
          },
          {
            "$ref": "#/components/parameters/RequestHeaders.clientRequestId"
          },
          {
            "$ref": "#/components/parameters/RequestHeaders.correlationRequestId"
          },
          {
            "$ref": "#/components/parameters/RequestHeaders.clientTenantId"
          },
          {
            "$ref": "#/components/parameters/RequestHeaders.homeTenantId"
          },
          {
            "$ref": "#/components/parameters/RequestHeaders.acceptLanguage"
          },
          {
            "$ref": "#/components/parameters/RequestHeaders.referer"
          },
          {
            "$ref": "#/components/parameters/RequestHeaders.traceparent"
          },
          {
            "$ref": "#/components/parameters/RequestHeaders.tracestate"
          }
        ],
        "responses": {
          "200": {
            "description": "Standard 200 OK response.",
            "headers": {
              "x-ms-request-id": {
                "required": true,
                "description": "Server-generated request ID.",
                "schema": {
                  "type": "string"
                }
              },
              "Date": {
                "required": true,
                "description": "The date the request was processed, in RFC 7231 format.",
                "schema": {
                  "type": "string"
                }
              }
            },
            "content": {
              "application/json": {
                "schema": {
                  "$ref": "#/components/schemas/Resource"
                }
              }
            }
          },
          "202": {
            "description": "Standard 202 Accepted response for long-running operations.",
            "headers": {
              "x-ms-request-id": {
                "required": true,
                "description": "Server-generated request ID.",
                "schema": {
                  "type": "string"
                }
              },
              "Date": {
                "required": true,
                "description": "The date the request was processed, in RFC 7231 format.",
                "schema": {
                  "type": "string"
                }
              }
            },
            "content": {
              "application/json": {
                "schema": {
                  "$ref": "#/components/schemas/LongRunningOperation"
                }
              }
            }
          },
          "4XX": {
            "description": "Generic error response for 4xx and 5xx status codes.",
            "headers": {
              "x-ms-request-id": {
                "required": true,
                "description": "Server-generated request ID.",
                "schema": {
                  "type": "string"
                }
              },
              "Date": {
                "required": true,
                "description": "The date the request was processed, in RFC 7231 format.",
                "schema": {
                  "type": "string"
                }
              }
            },
            "content": {
              "application/json": {
                "schema": {
                  "$ref": "#/components/schemas/ErrorResponse"
                }
              }
            }
          },
          "5XX": {
            "description": "Generic error response for 4xx and 5xx status codes.",
            "headers": {
              "x-ms-request-id": {
                "required": true,
                "description": "Server-generated request ID.",
                "schema": {
                  "type": "string"
                }
              },
              "Date": {
                "required": true,
                "description": "The date the request was processed, in RFC 7231 format.",
                "schema": {
                  "type": "string"
                }
              }
            },
            "content": {
              "application/json": {
                "schema": {
                  "$ref": "#/components/schemas/ErrorResponse"
                }
              }
            }
          }
        },
        "externalDocs": {
          "url": "https://github.com/Azure/bicep-extensibility/blob/main/docs/v2/contract.md#create-or-update-resource",
          "description": "Create or Update Resource Contract"
        },
        "requestBody": {
          "required": true,
          "content": {
            "application/json": {
              "schema": {
                "$ref": "#/components/schemas/ResourceSpecification"
              }
            }
          }
        }
      }
    },
    "/{extensionVersion}/resource/delete": {
      "post": {
        "operationId": "deleteResource",
        "description": "Delete a resource given its type, identifiers, configuration, and configuration ID.\n\nReturns 200 OK with a Resource if the operation completes synchronously or if the\nextension uses the RELO pattern (the resource will have a non-terminal status),\n204 No Content if the resource is deleted synchronously or does not exist, or\n202 Accepted with a LongRunningOperation if the deletion uses the LRO pattern.\n\nSee the [contract documentation](https://github.com/Azure/bicep-extensibility/blob/main/docs/v2/contract.md#delete-resource)\nfor detailed requirements.",
        "parameters": [
          {
            "$ref": "#/components/parameters/RequestParams.extensionVersion"
          },
          {
            "$ref": "#/components/parameters/RequestHeaders.clientRequestId"
          },
          {
            "$ref": "#/components/parameters/RequestHeaders.correlationRequestId"
          },
          {
            "$ref": "#/components/parameters/RequestHeaders.clientTenantId"
          },
          {
            "$ref": "#/components/parameters/RequestHeaders.homeTenantId"
          },
          {
            "$ref": "#/components/parameters/RequestHeaders.acceptLanguage"
          },
          {
            "$ref": "#/components/parameters/RequestHeaders.referer"
          },
          {
            "$ref": "#/components/parameters/RequestHeaders.traceparent"
          },
          {
            "$ref": "#/components/parameters/RequestHeaders.tracestate"
          }
        ],
        "responses": {
          "200": {
            "description": "Standard 200 OK response.",
            "headers": {
              "x-ms-request-id": {
                "required": true,
                "description": "Server-generated request ID.",
                "schema": {
                  "type": "string"
                }
              },
              "Date": {
                "required": true,
                "description": "The date the request was processed, in RFC 7231 format.",
                "schema": {
                  "type": "string"
                }
              }
            },
            "content": {
              "application/json": {
                "schema": {
                  "$ref": "#/components/schemas/Resource"
                }
              }
            }
          },
          "202": {
            "description": "Standard 202 Accepted response for long-running operations.",
            "headers": {
              "x-ms-request-id": {
                "required": true,
                "description": "Server-generated request ID.",
                "schema": {
                  "type": "string"
                }
              },
              "Date": {
                "required": true,
                "description": "The date the request was processed, in RFC 7231 format.",
                "schema": {
                  "type": "string"
                }
              }
            },
            "content": {
              "application/json": {
                "schema": {
                  "$ref": "#/components/schemas/LongRunningOperation"
                }
              }
            }
          },
          "204": {
            "description": "Standard 204 No Content response.",
            "headers": {
              "x-ms-request-id": {
                "required": true,
                "description": "Server-generated request ID.",
                "schema": {
                  "type": "string"
                }
              },
              "Date": {
                "required": true,
                "description": "The date the request was processed, in RFC 7231 format.",
                "schema": {
                  "type": "string"
                }
              }
            }
          },
          "4XX": {
            "description": "Generic error response for 4xx and 5xx status codes.",
            "headers": {
              "x-ms-request-id": {
                "required": true,
                "description": "Server-generated request ID.",
                "schema": {
                  "type": "string"
                }
              },
              "Date": {
                "required": true,
                "description": "The date the request was processed, in RFC 7231 format.",
                "schema": {
                  "type": "string"
                }
              }
            },
            "content": {
              "application/json": {
                "schema": {
                  "$ref": "#/components/schemas/ErrorResponse"
                }
              }
            }
          },
          "5XX": {
            "description": "Generic error response for 4xx and 5xx status codes.",
            "headers": {
              "x-ms-request-id": {
                "required": true,
                "description": "Server-generated request ID.",
                "schema": {
                  "type": "string"
                }
              },
              "Date": {
                "required": true,
                "description": "The date the request was processed, in RFC 7231 format.",
                "schema": {
                  "type": "string"
                }
              }
            },
            "content": {
              "application/json": {
                "schema": {
                  "$ref": "#/components/schemas/ErrorResponse"
                }
              }
            }
          }
        },
        "externalDocs": {
          "url": "https://github.com/Azure/bicep-extensibility/blob/main/docs/v2/contract.md#delete-resource",
          "description": "Delete Resource Contract"
        },
        "requestBody": {
          "required": true,
          "content": {
            "application/json": {
              "schema": {
                "$ref": "#/components/schemas/ResourceReference"
              }
            }
          }
        }
      }
    },
    "/{extensionVersion}/resource/get": {
      "post": {
        "operationId": "getResource",
        "description": "Get a resource given its type, identifiers, and configuration.\n\nReturns the current state of the resource, or 404 Not Found if it does not exist.\n\nSee the [contract documentation](https://github.com/Azure/bicep-extensibility/blob/main/docs/v2/contract.md#get-resource)\nfor detailed requirements.",
        "parameters": [
          {
            "$ref": "#/components/parameters/RequestParams.extensionVersion"
          },
          {
            "$ref": "#/components/parameters/RequestHeaders.clientRequestId"
          },
          {
            "$ref": "#/components/parameters/RequestHeaders.correlationRequestId"
          },
          {
            "$ref": "#/components/parameters/RequestHeaders.clientTenantId"
          },
          {
            "$ref": "#/components/parameters/RequestHeaders.homeTenantId"
          },
          {
            "$ref": "#/components/parameters/RequestHeaders.acceptLanguage"
          },
          {
            "$ref": "#/components/parameters/RequestHeaders.referer"
          },
          {
            "$ref": "#/components/parameters/RequestHeaders.traceparent"
          },
          {
            "$ref": "#/components/parameters/RequestHeaders.tracestate"
          }
        ],
        "responses": {
          "200": {
            "description": "Standard 200 OK response.",
            "headers": {
              "x-ms-request-id": {
                "required": true,
                "description": "Server-generated request ID.",
                "schema": {
                  "type": "string"
                }
              },
              "Date": {
                "required": true,
                "description": "The date the request was processed, in RFC 7231 format.",
                "schema": {
                  "type": "string"
                }
              }
            },
            "content": {
              "application/json": {
                "schema": {
                  "$ref": "#/components/schemas/Resource"
                }
              }
            }
          },
          "404": {
            "description": "Standard 404 Not Found error response.",
            "headers": {
              "x-ms-request-id": {
                "required": true,
                "description": "Server-generated request ID.",
                "schema": {
                  "type": "string"
                }
              },
              "Date": {
                "required": true,
                "description": "The date the request was processed, in RFC 7231 format.",
                "schema": {
                  "type": "string"
                }
              }
            },
            "content": {
              "application/json": {
                "schema": {
                  "$ref": "#/components/schemas/ErrorResponse"
                }
              }
            }
          },
          "4XX": {
            "description": "Generic error response for 4xx and 5xx status codes.",
            "headers": {
              "x-ms-request-id": {
                "required": true,
                "description": "Server-generated request ID.",
                "schema": {
                  "type": "string"
                }
              },
              "Date": {
                "required": true,
                "description": "The date the request was processed, in RFC 7231 format.",
                "schema": {
                  "type": "string"
                }
              }
            },
            "content": {
              "application/json": {
                "schema": {
                  "$ref": "#/components/schemas/ErrorResponse"
                }
              }
            }
          },
          "5XX": {
            "description": "Generic error response for 4xx and 5xx status codes.",
            "headers": {
              "x-ms-request-id": {
                "required": true,
                "description": "Server-generated request ID.",
                "schema": {
                  "type": "string"
                }
              },
              "Date": {
                "required": true,
                "description": "The date the request was processed, in RFC 7231 format.",
                "schema": {
                  "type": "string"
                }
              }
            },
            "content": {
              "application/json": {
                "schema": {
                  "$ref": "#/components/schemas/ErrorResponse"
                }
              }
            }
          }
        },
        "externalDocs": {
          "url": "https://github.com/Azure/bicep-extensibility/blob/main/docs/v2/contract.md#get-resource",
          "description": "Get Resource Contract"
        },
        "requestBody": {
          "required": true,
          "content": {
            "application/json": {
              "schema": {
                "$ref": "#/components/schemas/ResourceReference"
              }
            }
          }
        }
      }
    },
    "/{extensionVersion}/resource/preview": {
      "post": {
        "operationId": "previewResource",
        "description": "Preview a resource creation or update operation by simulating the process.\n\nSee the [contract documentation](https://github.com/Azure/bicep-extensibility/blob/main/docs/v2/contract.md#preview-resource)\nfor detailed requirements including handling of unevaluated expressions, preview metadata,\nconfiguration echoing, and configuration ID.",
        "parameters": [
          {
            "$ref": "#/components/parameters/RequestParams.extensionVersion"
          },
          {
            "$ref": "#/components/parameters/RequestHeaders.clientRequestId"
          },
          {
            "$ref": "#/components/parameters/RequestHeaders.correlationRequestId"
          },
          {
            "$ref": "#/components/parameters/RequestHeaders.clientTenantId"
          },
          {
            "$ref": "#/components/parameters/RequestHeaders.homeTenantId"
          },
          {
            "$ref": "#/components/parameters/RequestHeaders.acceptLanguage"
          },
          {
            "$ref": "#/components/parameters/RequestHeaders.referer"
          },
          {
            "$ref": "#/components/parameters/RequestHeaders.traceparent"
          },
          {
            "$ref": "#/components/parameters/RequestHeaders.tracestate"
          }
        ],
        "responses": {
          "200": {
            "description": "Standard 200 OK response.",
            "headers": {
              "x-ms-request-id": {
                "required": true,
                "description": "Server-generated request ID.",
                "schema": {
                  "type": "string"
                }
              },
              "Date": {
                "required": true,
                "description": "The date the request was processed, in RFC 7231 format.",
                "schema": {
                  "type": "string"
                }
              }
            },
            "content": {
              "application/json": {
                "schema": {
                  "$ref": "#/components/schemas/ResourcePreview"
                }
              }
            }
          },
          "4XX": {
            "description": "Generic error response for 4xx and 5xx status codes.",
            "headers": {
              "x-ms-request-id": {
                "required": true,
                "description": "Server-generated request ID.",
                "schema": {
                  "type": "string"
                }
              },
              "Date": {
                "required": true,
                "description": "The date the request was processed, in RFC 7231 format.",
                "schema": {
                  "type": "string"
                }
              }
            },
            "content": {
              "application/json": {
                "schema": {
                  "$ref": "#/components/schemas/ErrorResponse"
                }
              }
            }
          },
          "5XX": {
            "description": "Generic error response for 4xx and 5xx status codes.",
            "headers": {
              "x-ms-request-id": {
                "required": true,
                "description": "Server-generated request ID.",
                "schema": {
                  "type": "string"
                }
              },
              "Date": {
                "required": true,
                "description": "The date the request was processed, in RFC 7231 format.",
                "schema": {
                  "type": "string"
                }
              }
            },
            "content": {
              "application/json": {
                "schema": {
                  "$ref": "#/components/schemas/ErrorResponse"
                }
              }
            }
          }
        },
        "externalDocs": {
          "url": "https://github.com/Azure/bicep-extensibility/blob/main/docs/v2/contract.md#preview-resource",
          "description": "Preview Resource Contract"
        },
        "requestBody": {
          "required": true,
          "content": {
            "application/json": {
              "schema": {
                "$ref": "#/components/schemas/ResourcePreviewSpecification"
              }
            }
          }
        }
      }
    }
  },
  "components": {
    "parameters": {
      "RequestHeaders.acceptLanguage": {
        "name": "Accept-Language",
        "in": "header",
        "required": false,
        "description": "Specifies the preferred language for the response.\nExtensions should use this when generating client-facing text such as error messages.",
        "schema": {
          "type": "string"
        }
      },
      "RequestHeaders.clientRequestId": {
        "name": "x-ms-client-request-id",
        "in": "header",
        "required": true,
        "description": "Client-generated request ID for tracing.",
        "schema": {
          "type": "string"
        }
      },
      "RequestHeaders.clientTenantId": {
        "name": "x-ms-client-tenant-id",
        "in": "header",
        "required": false,
        "description": "The tenant ID of the client.",
        "schema": {
          "type": "string"
        }
      },
      "RequestHeaders.correlationRequestId": {
        "name": "x-ms-correlation-request-id",
        "in": "header",
        "required": true,
        "description": "Correlation request ID for cross-service tracing.",
        "schema": {
          "type": "string"
        }
      },
      "RequestHeaders.homeTenantId": {
        "name": "x-ms-home-tenant-id",
        "in": "header",
        "required": false,
        "description": "The home tenant ID of the client.",
        "schema": {
          "type": "string"
        }
      },
      "RequestHeaders.referer": {
        "name": "Referer",
        "in": "header",
        "required": true,
        "description": "The full URL of the extensibility host service instance from which the request is sent.\nExtensions should use this to track the source of the request.",
        "schema": {
          "type": "string"
        }
      },
      "RequestHeaders.traceparent": {
        "name": "traceparent",
        "in": "header",
        "required": true,
        "description": "Standard W3C trace context header for distributed tracing.\nExtensions should propagate this header if they support OpenTelemetry.",
        "schema": {
          "type": "string"
        }
      },
      "RequestHeaders.tracestate": {
        "name": "tracestate",
        "in": "header",
        "required": true,
        "description": "Standard W3C trace state header for vendor-specific trace data.\nExtensions should propagate this header if they support OpenTelemetry.",
        "schema": {
          "type": "string"
        }
      },
      "RequestParams.extensionVersion": {
        "name": "extensionVersion",
        "in": "path",
        "required": true,
        "description": "The semantic version of the extension.",
        "schema": {
          "type": "string"
        }
      }
    },
    "schemas": {
      "Error": {
        "type": "object",
        "required": [
          "code",
          "message"
        ],
        "properties": {
          "code": {
            "type": "string",
            "description": "A service-defined error code that classifies the error."
          },
          "message": {
            "type": "string",
            "description": "A human-readable description of the error."
          },
          "target": {
            "allOf": [
              {
                "$ref": "#/components/schemas/JsonPointer"
              }
            ],
            "description": "The target of the error.\nThis should be a JSON Pointer that indicates the location in the request\npayload that caused the error."
          },
          "details": {
            "type": "array",
            "items": {
              "$ref": "#/components/schemas/ErrorDetail"
            },
            "description": "An array of additional error details about specific errors that led to this reported error."
          },
          "innererror": {
            "type": "object",
            "additionalProperties": {},
            "description": "An object containing more specific information about the error.\nThe contents of this object are service-defined and may contain additional\nnested error information."
          }
        },
        "description": "Error model based on the OData v4 error response format.\n\nThe ARM Template deployment service converts this format to the ARM error\nresponse format before returning it to the client."
      },
      "ErrorDetail": {
        "type": "object",
        "required": [
          "code",
          "message"
        ],
        "properties": {
          "code": {
            "type": "string",
            "description": "A service-defined error code that classifies the error."
          },
          "message": {
            "type": "string",
            "description": "A human-readable description of the error."
          },
          "target": {
            "allOf": [
              {
                "$ref": "#/components/schemas/JsonPointer"
              }
            ],
            "description": "The target of the error.\nThis should be a JSON Pointer that indicates the location in the request\npayload that caused the error."
          }
        },
        "description": "Represents detailed information about an error, including a code, message,\nand an optional target reference."
      },
      "ErrorResponse": {
        "type": "object",
        "required": [
          "error"
        ],
        "properties": {
          "error": {
            "allOf": [
              {
                "$ref": "#/components/schemas/Error"
              }
            ],
            "description": "The error object containing detailed error information."
          }
        },
        "description": "A wrapper for Error to be used as an extensibility API error response."
      },
      "JsonPointer": {
        "type": "string",
        "description": "An RFC 6901 JSON Pointer string (e.g., \"/properties/name\").\nUsed throughout the API to reference specific locations in a JSON document."
      },
      "LongRunningOperation": {
        "type": "object",
        "required": [
          "status"
        ],
        "properties": {
          "status": {
            "allOf": [
              {
                "$ref": "#/components/schemas/OperationStatus"
              }
            ],
            "description": "The current status of the operation (e.g., \"Succeeded\", \"Failed\",\n\"Canceled\", or a non-terminal status like \"Running\")."
          },
          "retryAfterSeconds": {
            "type": "integer",
            "format": "int32",
            "description": "The recommended number of seconds to wait before polling the operation\nstatus again. If not specified, the caller defaults to a 60-second\npolling interval."
          },
          "operationHandle": {
            "type": "object",
            "additionalProperties": {},
            "description": "An opaque handle used to track and poll the operation.\nMust be specified if `status` is not terminal (i.e., not \"Succeeded\",\n\"Failed\", or \"Canceled\")."
          },
          "error": {
            "allOf": [
              {
                "$ref": "#/components/schemas/Error"
              }
            ],
            "description": "Error information if the operation failed.\nMust be set if `status` is \"Failed\" or \"Canceled\"."
          }
        },
        "description": "Represents the result of a long-running operation (LRO), including its\ncurrent status and optional retry, handle, and error information.\nUsed for stepwise long-running operations where the caller polls for\nstatus using the operation handle."
      },
      "OperationStatus": {
        "anyOf": [
          {
            "type": "string"
          },
          {
            "type": "string",
            "enum": [
              "Succeeded",
              "Failed",
              "Canceled"
            ]
          }
        ],
        "description": "Known terminal status values for resource and long-running operations.\n\nThe `string` member keeps the union open — extensions may define their own\nnon-terminal statuses (e.g., \"Running\", \"Provisioning\")."
      },
      "Resource": {
        "type": "object",
        "required": [
          "type",
          "identifiers",
          "properties"
        ],
        "properties": {
          "type": {
            "type": "string",
            "description": "The type of the resource."
          },
          "apiVersion": {
            "type": "string",
            "description": "The API version of the resource."
          },
          "identifiers": {
            "type": "object",
            "additionalProperties": {},
            "description": "The identifiers that, combined with the resource type and configuration,\nform a globally unique key for the resource. The extension must always\ninclude this in successful responses."
          },
          "properties": {
            "type": "object",
            "additionalProperties": {},
            "description": "The properties of the resource."
          },
          "config": {
            "type": "object",
            "additionalProperties": {},
            "description": "The configuration echoed back, with secret properties removed.\nMust be set if the resource has a configuration. Properties not echoed\nback are treated as secrets by the deployment engine."
          },
          "configId": {
            "type": "string",
            "description": "A checksum identifying the configuration.\nMust be set if the resource has a configuration. Used as a checksum\nfor subsequent operations such as deletion."
          },
          "status": {
            "allOf": [
              {
                "$ref": "#/components/schemas/OperationStatus"
              }
            ],
            "description": "The status of the resource. Used in RELO long-running operations where\na non-terminal status (e.g., \"Running\") indicates the operation is still\nin progress. Once the operation completes, this transitions to a terminal\nstate (\"Succeeded\", \"Failed\", or \"Canceled\")."
          },
          "error": {
            "allOf": [
              {
                "$ref": "#/components/schemas/Error"
              }
            ],
            "description": "Error information if the long-running resource operation failed.\nThis should only be set if `status` is \"Failed\"."
          }
        },
        "description": "Represents an instance of a resource returned from the create or update,\nget, or delete operations."
      },
      "ResourcePreview": {
        "type": "object",
        "required": [
          "type",
          "identifiers",
          "properties"
        ],
        "properties": {
          "type": {
            "type": "string",
            "description": "The type of the resource."
          },
          "apiVersion": {
            "type": "string",
            "description": "The API version of the resource."
          },
          "identifiers": {
            "type": "object",
            "additionalProperties": {},
            "description": "The identifiers that uniquely identify the resource."
          },
          "properties": {
            "type": "object",
            "additionalProperties": {},
            "description": "The properties of the previewed resource. Should include read-only\nproperties and default values. Write-only properties (e.g., passwords)\nshould be excluded. Unevaluated expressions should be echoed as-is."
          },
          "status": {
            "allOf": [
              {
                "$ref": "#/components/schemas/OperationStatus"
              }
            ],
            "description": "The status of the resource."
          },
          "config": {
            "type": "object",
            "additionalProperties": {},
            "description": "The configuration echoed back, with secret properties removed.\nMust be set if the resource has a configuration."
          },
          "configId": {
            "type": "string",
            "description": "A checksum identifying the configuration.\nMust be set if the resource has a configuration."
          },
          "metadata": {
            "allOf": [
              {
                "$ref": "#/components/schemas/ResourcePreviewMetadata"
              }
            ],
            "description": "Metadata describing which properties in the preview are read-only,\nimmutable, unknown, calculated, or unevaluated. Providing this metadata\nenables a more accurate and detailed preview experience for the end user."
          }
        },
        "description": "Represents a preview of a resource, returned from the preview operation.\nThe preview should mirror what a get response would return as if the\ncreate or update operation had been performed, including read-only\nproperties and properties with default values, and excluding write-only\nproperties such as passwords."
      },
      "ResourcePreviewMetadata": {
        "type": "object",
        "properties": {
          "readOnly": {
            "type": "array",
            "items": {
              "$ref": "#/components/schemas/JsonPointer"
            },
            "description": "JSON Pointers to properties that are read-only.\nThese properties are managed by the service and cannot be set by the client."
          },
          "immutable": {
            "type": "array",
            "items": {
              "$ref": "#/components/schemas/JsonPointer"
            },
            "description": "JSON Pointers to properties that are immutable.\nThese properties can be set during resource creation but cannot be\nchanged later."
          },
          "unknown": {
            "type": "array",
            "items": {
              "$ref": "#/components/schemas/JsonPointer"
            },
            "description": "JSON Pointers to properties whose values cannot be determined at preview\ntime (e.g., because they depend on unevaluated expressions or external\nstate)."
          },
          "calculated": {
            "type": "array",
            "items": {
              "$ref": "#/components/schemas/JsonPointer"
            },
            "description": "JSON Pointers to properties whose values are calculated at operation time\nand would change if the operation were performed later (e.g., timestamps)."
          },
          "unevaluated": {
            "type": "array",
            "items": {
              "$ref": "#/components/schemas/JsonPointer"
            },
            "description": "JSON Pointers to properties containing unevaluated ARM template language\nexpressions. The extension must echo these back from the request.\nA property in `unevaluated` in the request may be reclassified in the\nresponse (e.g., as `readOnly` or `immutable`) if the extension can\ndetermine the property's nature despite the unevaluated expression."
          }
        },
        "description": "Contains metadata about a resource preview, indicating which properties\nare read-only, immutable, unknown, calculated, or unevaluated."
      },
      "ResourcePreviewSpecification": {
        "type": "object",
        "properties": {
          "metadata": {
            "allOf": [
              {
                "$ref": "#/components/schemas/ResourcePreviewSpecificationMetadata"
              }
            ],
            "description": "Optional metadata for the preview specification, such as properties that\ncould not be evaluated."
          }
        },
        "allOf": [
          {
            "$ref": "#/components/schemas/ResourceSpecification"
          }
        ],
        "description": "Represents the specification for a resource preview request.\nExtends ResourceSpecification with optional preview metadata."
      },
      "ResourcePreviewSpecificationMetadata": {
        "type": "object",
        "required": [
          "unevaluated"
        ],
        "properties": {
          "unevaluated": {
            "type": "array",
            "items": {
              "$ref": "#/components/schemas/JsonPointer"
            },
            "description": "JSON Pointers to the properties that could not be evaluated during the\npreview. The values of these properties are ARM template expressions\n(e.g., [reference(...)])."
          }
        },
        "description": "Contains metadata for a resource preview specification, indicating which\nproperties could not be evaluated at the time of the preview request."
      },
      "ResourceReference": {
        "type": "object",
        "required": [
          "type",
          "identifiers"
        ],
        "properties": {
          "type": {
            "type": "string",
            "description": "The type of the resource."
          },
          "apiVersion": {
            "type": "string",
            "description": "The API version of the resource."
          },
          "identifiers": {
            "type": "object",
            "additionalProperties": {},
            "description": "The identifier properties that, combined with the resource type and\nconfiguration, form a globally unique key for the resource.\nThe structure is defined by the extension and is opaque to the\ndeployment engine."
          },
          "config": {
            "type": "object",
            "additionalProperties": {},
            "description": "The extension configuration for the resource, if any."
          },
          "configId": {
            "type": "string",
            "description": "A checksum identifying the configuration.\nIf present, the extension should validate it against the config.\nRequired for delete operations when a configuration is present."
          }
        },
        "description": "Represents a reference to a resource, containing the information needed to\nuniquely identify it (type, API version, identifiers, and optional config).\nUsed as input to get and delete operations."
      },
      "ResourceSpecification": {
        "type": "object",
        "required": [
          "type",
          "properties"
        ],
        "properties": {
          "type": {
            "type": "string",
            "description": "The type of the resource."
          },
          "apiVersion": {
            "type": "string",
            "description": "The API version of the resource."
          },
          "properties": {
            "type": "object",
            "additionalProperties": {},
            "description": "The desired properties of the resource."
          },
          "config": {
            "type": "object",
            "additionalProperties": {},
            "description": "The extension configuration.\nThe extension should echo this back in the response, minus any secret\nproperties. Properties not echoed back are treated as secrets by the\ndeployment engine."
          },
          "configId": {
            "type": "string",
            "description": "A checksum identifying the configuration.\n\nThis is only set when the request is sent from the Deployment Stacks service.\nExtensions should calculate the config ID based on the config and compare it\nwith this value. If they don't match, the extension should reject the request."
          }
        },
        "description": "Represents what the user declares in their template to specify the desired\nstate of a resource. Used as input to create or update operations."
      },
      "ResponseHeaders": {
        "type": "object"
      }
    }
  },
  "servers": [
    {
      "url": "{endpoint}",
      "description": "Extension endpoint",
      "variables": {
        "endpoint": {
          "default": "http://localhost:8080"
        }
      }
    }
  ]
}
